lyymysql
