Metadata-Version: 2.1
Name: lyymysql
Version: 1.4
Summary: userfull application for  lyy
Author: lyy
Author-email: 
License: MIT
License-File: LICENSE
